ejabberd_extauth_oidc_password.py
ejabberd_extauth_oidc_password-1.0.1.dist-info/METADATA
ejabberd_extauth_oidc_password-1.0.1.dist-info/WHEEL
ejabberd_extauth_oidc_password-1.0.1.dist-info/entry_points.txt
ejabberd_extauth_oidc_password-1.0.1.dist-info/RECORD
