Metadata-Version: 2.1
Name: ejabberd-extauth-oidc-password
Version: 1.0.1
Summary: ejabberd extauth script to use OpenID Connect with the Resource Owner Password Grant Flow
Home-page: https://codeberg.org/Natureshadow/ejabberd-extauth-oidc-password
License: MIT
Keywords: ejabberd,xmpp,oidc
Author: Dominik George
Author-email: nik@naturalnet.de
Requires-Python: >=3.11,<4.0
Classifier: Intended Audience :: System Administrators
Classifier: License :: OSI Approved :: MIT License
Classifier: Programming Language :: Python :: 3
Classifier: Programming Language :: Python :: 3.11
Classifier: Programming Language :: Python :: 3.12
Classifier: Topic :: Communications :: Chat
Classifier: Topic :: Internet :: XMPP
Requires-Dist: ejabberd-extauth (>=1.0.0,<2.0.0)
Requires-Dist: pydantic (>=2.8.2,<3.0.0)
Requires-Dist: requests-oauthlib (>=2.0.0,<3.0.0)
Project-URL: Repository, https://codeberg.org/Natureshadow/ejabberd-extauth-oidc-password
